<?xml version="1.0"?>
<mavlink>
  <!-- MAVLink standard messages -->
  <include>minimal.xml</include>
  <dialect>0</dialect>
  <!-- use common.xml enums -->
  <enums/>
  <!-- use common.xml messages -->
  <messages>
    <message id="180" name="ECUU_ENGINE_STATE">
        <description>ECUU Engines state</description>
        <field type="uint16_t" name="rpm">RPM</field>
        <field type="uint16_t" name="egt">Exhaust gas temperature</field>
        <field type="uint16_t" name="fuelFlow">Fuel flow (ml/min)</field>
        <field type="uint16_t" name="setThrottle">Throttle setpoint (in 0.1%)</field>
        <field type="uint8_t"  name="batVoltage">Battery voltage</field>
        <field type="uint8_t"  name="batCurrent">Battery current</field>
    </message>
    <message id="30000" name="ECUU_ENGINE_STATE2">
        <description>ECUU Extended state</description>
        <field type="uint8_t" name="target_system">System ID</field>
        <field type="uint8_t" name="target_component">Component ID</field>
        <field type="uint8_t[64]" name="data">Payload</field>
    </message>
  </messages>
</mavlink>
